zq_django_util/__init__.py
zq_django_util/exceptions/__init__.py
zq_django_util/exceptions/configs.py
zq_django_util/exceptions/handler.py
zq_django_util/exceptions/types.py
zq_django_util/exceptions/views.py
zq_django_util/logs/__init__.py
zq_django_util/logs/admin.py
zq_django_util/logs/apps.py
zq_django_util/logs/configs.py
zq_django_util/logs/handler.py
zq_django_util/logs/middleware.py
zq_django_util/logs/migrations/0001_initial.py
zq_django_util/logs/migrations/0002_alter_requestlog_content_type_and_more.py
zq_django_util/logs/migrations/__init__.py
zq_django_util/logs/models.py
zq_django_util/logs/templates/change_form.html
zq_django_util/logs/templates/charts_change_list.html
zq_django_util/logs/threads.py
zq_django_util/logs/types.py
zq_django_util/logs/utils.py
zq_django_util/response/__init__.py
zq_django_util/response/renderers.py
zq_django_util/response/types.py
zq_django_util/utils/__init__.py
zq_django_util/utils/auth/__init__.py
zq_django_util/utils/auth/authentications.py
zq_django_util/utils/auth/backends.py
zq_django_util/utils/auth/exceptions.py
zq_django_util/utils/auth/serializers.py
zq_django_util/utils/auth/views.py
zq_django_util/utils/meili/__init__.py
zq_django_util/utils/meili/constant/__init__.py
zq_django_util/utils/meili/constant/error.py
zq_django_util/utils/meili/constant/task.py
zq_django_util/utils/meili/error.py
zq_django_util/utils/meili/exceptions.py
zq_django_util/utils/meili/index.py
zq_django_util/utils/meili/pagination.py
zq_django_util/utils/meili/response.py
zq_django_util/utils/meili/task.py
zq_django_util/utils/mixins.py
zq_django_util/utils/oss/__init__.py
zq_django_util/utils/oss/backends.py
zq_django_util/utils/oss/configs.py
zq_django_util/utils/oss/exceptions.py
zq_django_util/utils/oss/utils.py
zq_django_util/utils/package_settings.py
zq_django_util/utils/pagination.py
zq_django_util/utils/types.py
zq_django_util/utils/user/__init__.py
zq_django_util/utils/user/models.py
zq_django_util/utils/views.py
zq_django_util-0.2.2.dist-info/LICENSE.txt
zq_django_util-0.2.2.dist-info/METADATA
zq_django_util-0.2.2.dist-info/WHEEL
zq_django_util-0.2.2.dist-info/RECORD
