Metadata-Version: 2.1
Name: zq-django-util
Version: 0.2.2
Summary: 自强Studio Django 工具
Home-page: https://github.com/Nagico/zq-django-util
License: MIT
Keywords: django,drf,util
Author: Nagico
Author-email: yjr888@vip.qq.com
Requires-Python: >=3.8,<4.0
Classifier: License :: OSI Approved :: MIT License
Classifier: Programming Language :: Python :: 3
Classifier: Programming Language :: Python :: 3.8
Classifier: Programming Language :: Python :: 3.9
Classifier: Programming Language :: Python :: 3.10
Classifier: Programming Language :: Python :: 3.11
Provides-Extra: sentry
Requires-Dist: django-cleanup (>=6.0.0,<7.0.0)
Requires-Dist: djangorestframework-simplejwt (>=4.7,<6.0)
Requires-Dist: drf-standardized-errors (>=0.9.0,<0.13.0)
Requires-Dist: isodate (>=0.6.1,<0.7.0)
Requires-Dist: oss2 (>=2.13.0,<3.0)
Project-URL: Documentation, https://zq-django-util.readthedocs.io/en/latest/
